abr/__init__.py
abr/abr-icon.ico
abr/abr-icon.png
abr/abrpanel.py
abr/compare.py
abr/compare_window.enaml
abr/datatype.py
abr/launch_window.enaml
abr/main.py
abr/main_window.enaml
abr/peakdetect.py
abr/presenter.py
abr/util.py
abr/version.py
abr/data/ABR-52-3
abr/data/CAP-139-5
abr/data/CAP-139-5-16.0kHz-Brad-analyzed.txt
abr/data/CAP-139-5-16.0kHz-analyzed.txt
abr/parsers/EPL.py
abr/parsers/NCRAR.py
abr/parsers/PSI.py
abr/parsers/__init__.py
abr/parsers/dataset.py
scripts/make_icon.py
ABR-0.0.14.dist-info/LICENSE.txt
ABR-0.0.14.dist-info/METADATA
ABR-0.0.14.dist-info/WHEEL
ABR-0.0.14.dist-info/entry_points.txt
ABR-0.0.14.dist-info/top_level.txt
ABR-0.0.14.dist-info/RECORD
