Metadata-Version: 2.1
Name: ABR
Version: 0.0.14
Summary: Evoked potential analysis software
Author-email: Brad Buran <bburan@alum.mit.edu>, Brad Buran <buran@ohsu.edu>
Maintainer-email: Brad Buran <bburan@alum.mit.edu>, Brad Buran <buran@ohsu.edu>
License: BSD 3-Clause License
Project-URL: homepage, https://github.com/bburan/abr
Project-URL: documentation, https://github.com/bburan/abr
Project-URL: repository, https://github.com/bburan/abr
Classifier: Operating System :: OS Independent
Classifier: Programming Language :: Python :: 3
Classifier: License :: OSI Approved :: BSD License
Requires-Python: >=3.7
License-File: LICENSE.txt
Requires-Dist: atom
Requires-Dist: enaml[qt6-pyside]
Requires-Dist: numpy
Requires-Dist: scipy
Requires-Dist: pandas
Requires-Dist: matplotlib
